anyblok_wms_base/__init__.py
anyblok_wms_base/constants.py
anyblok_wms_base/exceptions.py
anyblok_wms_base/sdtestcase.py
anyblok_wms_base/testing.py
anyblok_wms_base/utils.py
anyblok_wms_base/core/__init__.py
anyblok_wms_base/core/location.py
anyblok_wms_base/core/wms.py
anyblok_wms_base/core/goods/__init__.py
anyblok_wms_base/core/goods/goods.py
anyblok_wms_base/core/goods/type.py
anyblok_wms_base/core/goods/tests/__init__.py
anyblok_wms_base/core/goods/tests/test_type.py
anyblok_wms_base/core/operation/__init__.py
anyblok_wms_base/core/operation/arrival.py
anyblok_wms_base/core/operation/assembly.py
anyblok_wms_base/core/operation/base.py
anyblok_wms_base/core/operation/departure.py
anyblok_wms_base/core/operation/move.py
anyblok_wms_base/core/operation/ns.py
anyblok_wms_base/core/operation/single_input.py
anyblok_wms_base/core/operation/unpack.py
anyblok_wms_base/core/operation/tests/__init__.py
anyblok_wms_base/core/operation/tests/test_arrival.py
anyblok_wms_base/core/operation/tests/test_assembly.py
anyblok_wms_base/core/operation/tests/test_departure.py
anyblok_wms_base/core/operation/tests/test_move.py
anyblok_wms_base/core/operation/tests/test_operation.py
anyblok_wms_base/core/operation/tests/test_single_input.py
anyblok_wms_base/core/operation/tests/test_unpack.py
anyblok_wms_base/core/operation/tests/testcase.py
anyblok_wms_base/core/tests/__init__.py
anyblok_wms_base/core/tests/test_exceptions.py
anyblok_wms_base/core/tests/test_goods.py
anyblok_wms_base/core/tests/test_goods_quantity.py
anyblok_wms_base/core/tests/test_location.py
anyblok_wms_base/core/tests/test_testing.py
anyblok_wms_base/quantity/__init__.py
anyblok_wms_base/quantity/goods.py
anyblok_wms_base/quantity/wms.py
anyblok_wms_base/quantity/operation/__init__.py
anyblok_wms_base/quantity/operation/aggregate.py
anyblok_wms_base/quantity/operation/arrival.py
anyblok_wms_base/quantity/operation/move.py
anyblok_wms_base/quantity/operation/split.py
anyblok_wms_base-0.7.0.dist-info/LICENSE.txt
anyblok_wms_base-0.7.0.dist-info/METADATA
anyblok_wms_base-0.7.0.dist-info/RECORD
anyblok_wms_base-0.7.0.dist-info/WHEEL
anyblok_wms_base-0.7.0.dist-info/entry_points.txt
anyblok_wms_base-0.7.0.dist-info/top_level.txt
