Metadata-Version: 2.1
Name: anyblok-wms-base
Version: 0.7.0
Summary: Warehouse Management and Logistics, base Anyblok modules
Home-page: http://docs.anyblok-wms-base.anyblok.org/0.7.0
Author: Georges Racinet
Author-email: gracinet@anybox.fr
License: UNKNOWN
Keywords: stock logistics wms
Platform: UNKNOWN
Classifier: Development Status :: 2 - Pre-Alpha
Classifier: Intended Audience :: Developers
Classifier: Programming Language :: Python :: 3
Classifier: Programming Language :: Python :: 3.5
Classifier: Programming Language :: Python :: 3.6
Classifier: Programming Language :: Python :: 3.7
Requires-Dist: anyblok (>=0.18.0)
Requires-Dist: anyblok-postgres
Requires-Dist: psycopg2
